[
  {
    "name": "TI99_Tools",
    "version": "char-v1.0.9308.24614",
    "published": "2025-06-26T13:40:37Z",
    "download": "https://github.com/miriki/TI99_Tools/releases/download/char-v1.0.9308.24614/TI99_Char_Tools.exe",
    "exe": "TI99_Char_Tools.exe",
    "tag_prefix": "char"
  },
  {
    "name": "TI99_Tools",
    "version": "char-v1.0.9308.24614",
    "published": "2025-06-26T13:40:37Z",
    "download": "https://github.com/miriki/TI99_Tools/releases/download/char-v1.0.9308.24614/TI99_Char_Tools.exe",
    "exe": "TI99_Disk_Tools.exe",
    "tag_prefix": "disk"
  }
]